sql_query/__init__.py
sql_query/sql_query.py
sql_queries-0.1.2.dist-info/LICENSE
sql_queries-0.1.2.dist-info/METADATA
sql_queries-0.1.2.dist-info/WHEEL
sql_queries-0.1.2.dist-info/top_level.txt
sql_queries-0.1.2.dist-info/RECORD
