Metadata-Version: 2.1
Name: sql-queries
Version: 0.1.2
Summary: Build simple SQL queries fast and clean
Home-page: https://pypi.org/project/sql-queries/
Author: Simon van Meegdenburg
Author-email: simonvm@live.nl
License: UNKNOWN
Platform: UNKNOWN
Classifier: Programming Language :: Python :: 3
Classifier: Programming Language :: SQL
Classifier: License :: OSI Approved :: GNU General Public License v3 (GPLv3)
Classifier: Operating System :: OS Independent
Classifier: Development Status :: 3 - Alpha
Classifier: Natural Language :: English
Classifier: Topic :: Database
Requires-Python: >=3.6
